{"id":"VariableCollectionId:58:7503","name":"Primitives","modes":{"58:0":"Mode 1"},"variableIds":["VariableID:58:7504","VariableID:58:7506","VariableID:58:7508","VariableID:58:7510","VariableID:58:7512","VariableID:58:7514","VariableID:58:7516","VariableID:58:7518","VariableID:58:7520","VariableID:58:7522","VariableID:105:5351","VariableID:105:5352","VariableID:105:5353","VariableID:105:5354","VariableID:105:5355","VariableID:105:5356","VariableID:105:5357","VariableID:105:5358","VariableID:105:5359","VariableID:105:5360","VariableID:105:5361","VariableID:105:5362","VariableID:105:5363","VariableID:105:5364","VariableID:105:5365","VariableID:105:5366","VariableID:105:5367","VariableID:105:5368","VariableID:105:5369","VariableID:105:5370","VariableID:105:5371","VariableID:105:5372","VariableID:105:5373","VariableID:105:5374","VariableID:105:5375","VariableID:105:5376","VariableID:105:5377","VariableID:105:5378","VariableID:105:5379","VariableID:105:5380","VariableID:105:5381","VariableID:105:5382","VariableID:105:5383","VariableID:105:5384","VariableID:105:5385","VariableID:105:5386","VariableID:105:5387","VariableID:105:5388","VariableID:105:5389","VariableID:105:5390","VariableID:105:5391","VariableID:105:5392","VariableID:105:5393","VariableID:105:5394","VariableID:105:5395","VariableID:105:5396","VariableID:105:5397","VariableID:105:5398","VariableID:105:5399","VariableID:105:5400","VariableID:105:5401","VariableID:105:5402","VariableID:105:5403","VariableID:105:5404","VariableID:105:5405","VariableID:105:5406","VariableID:105:5407","VariableID:105:5408","VariableID:105:5409","VariableID:105:5410","VariableID:105:5411","VariableID:105:5412","VariableID:105:5413","VariableID:105:5414","VariableID:105:5415","VariableID:105:5416","VariableID:105:5417","VariableID:105:5418","VariableID:105:5419","VariableID:105:5420","VariableID:105:5421","VariableID:105:5422","VariableID:105:5423","VariableID:105:5424","VariableID:105:5425","VariableID:105:5426","VariableID:105:5427","VariableID:105:5428","VariableID:105:5429","VariableID:105:5430","VariableID:105:5431","VariableID:105:5432","VariableID:105:5433","VariableID:105:5434","VariableID:105:5435","VariableID:105:5436","VariableID:105:5437","VariableID:105:5438","VariableID:105:5439","VariableID:65:9628","VariableID:105:5440","VariableID:65:9629","VariableID:151:6271","VariableID:151:6272","VariableID:151:6266","VariableID:151:6267","VariableID:151:6268","VariableID:151:6269","VariableID:151:6270","VariableID:151:7756","VariableID:151:7757","VariableID:151:7758","VariableID:151:7759","VariableID:151:7760","VariableID:151:7761","VariableID:151:7762","VariableID:151:7763","VariableID:151:7764","VariableID:151:7765","VariableID:151:7773","VariableID:151:7774","VariableID:151:7775","VariableID:151:7776","VariableID:151:7777","VariableID:151:7778","VariableID:151:7779","VariableID:151:7780","VariableID:151:7781","VariableID:151:7766","VariableID:151:7767","VariableID:151:7768","VariableID:151:7769","VariableID:151:7770","VariableID:151:7771","VariableID:151:7782","VariableID:151:7783","VariableID:151:7784","VariableID:210:472","VariableID:210:473","VariableID:210:474","VariableID:210:475","VariableID:210:476","VariableID:210:477","VariableID:151:7785"],"variables":[{"id":"VariableID:58:7504","name":"Color/Grey/50","description":"","type":"COLOR","valuesByMode":{"58:0":{"r":0.9490196108818054,"g":0.9529411792755127,"b":0.9529411792755127,"a":1}},"resolvedValuesByMode":{"58:0":{"resolvedValue":{"r":0.9490196108818054,"g":0.9529411792755127,"b":0.9529411792755127,"a":1},"alias":null}},"scopes":["ALL_SCOPES"],"hiddenFromPublishing":false,"codeSyntax":{}},{"id":"VariableID:58:7506","name":"Color/Grey/100","description":"","type":"COLOR","valuesByMode":{"58:0":{"r":0.8470588326454163,"g":0.8509804010391235,"b":0.8588235378265381,"a":1}},"resolvedValuesByMode":{"58:0":{"resolvedValue":{"r":0.8470588326454163,"g":0.8509804010391235,"b":0.8588235378265381,"a":1},"alias":null}},"scopes":["ALL_SCOPES"],"hiddenFromPublishing":false,"codeSyntax":{}},{"id":"VariableID:58:7508","name":"Color/Grey/200","description":"","type":"COLOR","valuesByMode":{"58:0":{"r":0.772549033164978,"g":0.7764706015586853,"b":0.7882353067398071,"a":1}},"resolvedValuesByMode":{"58:0":{"resolvedValue":{"r":0.772549033164978,"g":0.7764706015586853,"b":0.7882353067398071,"a":1},"alias":null}},"scopes":["ALL_SCOPES"],"hiddenFromPublishing":false,"codeSyntax":{}},{"id":"VariableID:58:7510","name":"Color/Grey/300","description":"","type":"COLOR","valuesByMode":{"58:0":{"r":0.6705882549285889,"g":0.6745098233222961,"b":0.6941176652908325,"a":1}},"resolvedValuesByMode":{"58:0":{"resolvedValue":{"r":0.6705882549285889,"g":0.6745098233222961,"b":0.6941176652908325,"a":1},"alias":null}},"scopes":["ALL_SCOPES"],"hiddenFromPublishing":false,"codeSyntax":{}},{"id":"VariableID:58:7512","name":"Color/Grey/400","description":"","type":"COLOR","valuesByMode":{"58:0":{"r":0.6039215922355652,"g":0.6117647290229797,"b":0.6313725709915161,"a":1}},"resolvedValuesByMode":{"58:0":{"resolvedValue":{"r":0.6039215922355652,"g":0.6117647290229797,"b":0.6313725709915161,"a":1},"alias":null}},"scopes":["ALL_SCOPES"],"hiddenFromPublishing":false,"codeSyntax":{}},{"id":"VariableID:58:7514","name":"Color/Grey/500","description":"","type":"COLOR","valuesByMode":{"58:0":{"r":0.5058823823928833,"g":0.5137255191802979,"b":0.5411764979362488,"a":1}},"resolvedValuesByMode":{"58:0":{"resolvedValue":{"r":0.5058823823928833,"g":0.5137255191802979,"b":0.5411764979362488,"a":1},"alias":null}},"scopes":["ALL_SCOPES"],"hiddenFromPublishing":false,"codeSyntax":{}},{"id":"VariableID:58:7516","name":"Color/Grey/600","description":"","type":"COLOR","valuesByMode":{"58:0":{"r":0.4588235318660736,"g":0.46666666865348816,"b":0.4941176474094391,"a":1}},"resolvedValuesByMode":{"58:0":{"resolvedValue":{"r":0.4588235318660736,"g":0.46666666865348816,"b":0.4941176474094391,"a":1},"alias":null}},"scopes":["ALL_SCOPES"],"hiddenFromPublishing":false,"codeSyntax":{}},{"id":"VariableID:58:7518","name":"Color/Grey/700","description":"","type":"COLOR","valuesByMode":{"58:0":{"r":0.3607843220233917,"g":0.364705890417099,"b":0.3843137323856354,"a":1}},"resolvedValuesByMode":{"58:0":{"resolvedValue":{"r":0.3607843220233917,"g":0.364705890417099,"b":0.3843137323856354,"a":1},"alias":null}},"scopes":["ALL_SCOPES"],"hiddenFromPublishing":false,"codeSyntax":{}},{"id":"VariableID:58:7520","name":"Color/Grey/800","description":"","type":"COLOR","valuesByMode":{"58:0":{"r":0.27843138575553894,"g":0.2823529541492462,"b":0.2980392277240753,"a":1}},"resolvedValuesByMode":{"58:0":{"resolvedValue":{"r":0.27843138575553894,"g":0.2823529541492462,"b":0.2980392277240753,"a":1},"alias":null}},"scopes":["ALL_SCOPES"],"hiddenFromPublishing":false,"codeSyntax":{}},{"id":"VariableID:58:7522","name":"Color/Grey/900","description":"","type":"COLOR","valuesByMode":{"58:0":{"r":0.21176470816135406,"g":0.21568627655506134,"b":0.22745098173618317,"a":1}},"resolvedValuesByMode":{"58:0":{"resolvedValue":{"r":0.21176470816135406,"g":0.21568627655506134,"b":0.22745098173618317,"a":1},"alias":null}},"scopes":["ALL_SCOPES"],"hiddenFromPublishing":false,"codeSyntax":{}},{"id":"VariableID:65:9628","name":"Color/Black","description":"","type":"COLOR","valuesByMode":{"58:0":{"r":0.14509804546833038,"g":0.14509804546833038,"b":0.14509804546833038,"a":1}},"resolvedValuesByMode":{"58:0":{"resolvedValue":{"r":0.14509804546833038,"g":0.14509804546833038,"b":0.14509804546833038,"a":1},"alias":null}},"scopes":["ALL_SCOPES"],"hiddenFromPublishing":false,"codeSyntax":{}},{"id":"VariableID:65:9629","name":"Color/White","description":"","type":"COLOR","valuesByMode":{"58:0":{"r":0.9450980424880981,"g":0.9450980424880981,"b":0.9490196108818054,"a":1}},"resolvedValuesByMode":{"58:0":{"resolvedValue":{"r":0.9450980424880981,"g":0.9450980424880981,"b":0.9490196108818054,"a":1},"alias":null}},"scopes":["ALL_SCOPES"],"hiddenFromPublishing":false,"codeSyntax":{}},{"id":"VariableID:105:5351","name":"Color/Ccharcole/50","description":"","type":"COLOR","valuesByMode":{"58:0":{"r":0.9333333373069763,"g":0.9333333373069763,"b":0.9372549057006836,"a":1}},"resolvedValuesByMode":{"58:0":{"resolvedValue":{"r":0.9333333373069763,"g":0.9333333373069763,"b":0.9372549057006836,"a":1},"alias":null}},"scopes":["ALL_SCOPES"],"hiddenFromPublishing":false,"codeSyntax":{}},{"id":"VariableID:105:5352","name":"Color/Ccharcole/100","description":"","type":"COLOR","valuesByMode":{"58:0":{"r":0.7882353067398071,"g":0.7960784435272217,"b":0.800000011920929,"a":1}},"resolvedValuesByMode":{"58:0":{"resolvedValue":{"r":0.7882353067398071,"g":0.7960784435272217,"b":0.800000011920929,"a":1},"alias":null}},"scopes":["ALL_SCOPES"],"hiddenFromPublishing":false,"codeSyntax":{}},{"id":"VariableID:105:5353","name":"Color/Ccharcole/200","description":"","type":"COLOR","valuesByMode":{"58:0":{"r":0.686274528503418,"g":0.6941176652908325,"b":0.7058823704719543,"a":1}},"resolvedValuesByMode":{"58:0":{"resolvedValue":{"r":0.686274528503418,"g":0.6941176652908325,"b":0.7058823704719543,"a":1},"alias":null}},"scopes":["ALL_SCOPES"],"hiddenFromPublishing":false,"codeSyntax":{}},{"id":"VariableID:105:5354","name":"Color/Ccharcole/300","description":"","type":"COLOR","valuesByMode":{"58:0":{"r":0.545098066329956,"g":0.5568627715110779,"b":0.5686274766921997,"a":1}},"resolvedValuesByMode":{"58:0":{"resolvedValue":{"r":0.545098066329956,"g":0.5568627715110779,"b":0.5686274766921997,"a":1},"alias":null}},"scopes":["ALL_SCOPES"],"hiddenFromPublishing":false,"codeSyntax":{}},{"id":"VariableID:105:5355","name":"Color/Ccharcole/400","description":"","type":"COLOR","valuesByMode":{"58:0":{"r":0.4588235318660736,"g":0.47058823704719543,"b":0.48627451062202454,"a":1}},"resolvedValuesByMode":{"58:0":{"resolvedValue":{"r":0.4588235318660736,"g":0.47058823704719543,"b":0.48627451062202454,"a":1},"alias":null}},"scopes":["ALL_SCOPES"],"hiddenFromPublishing":false,"codeSyntax":{}},{"id":"VariableID:105:5356","name":"Color/Ccharcole/500","description":"","type":"COLOR","valuesByMode":{"58:0":{"r":0.32156863808631897,"g":0.33725491166114807,"b":0.35686275362968445,"a":1}},"resolvedValuesByMode":{"58:0":{"resolvedValue":{"r":0.32156863808631897,"g":0.33725491166114807,"b":0.35686275362968445,"a":1},"alias":null}},"scopes":["ALL_SCOPES"],"hiddenFromPublishing":false,"codeSyntax":{}},{"id":"VariableID:105:5357","name":"Color/Ccharcole/600","description":"","type":"COLOR","valuesByMode":{"58:0":{"r":0.29411765933036804,"g":0.30588236451148987,"b":0.32549020648002625,"a":1}},"resolvedValuesByMode":{"58:0":{"resolvedValue":{"r":0.29411765933036804,"g":0.30588236451148987,"b":0.32549020648002625,"a":1},"alias":null}},"scopes":["ALL_SCOPES"],"hiddenFromPublishing":false,"codeSyntax":{}},{"id":"VariableID:105:5358","name":"Color/Ccharcole/700","description":"","type":"COLOR","valuesByMode":{"58:0":{"r":0.22745098173618317,"g":0.239215686917305,"b":0.2549019753932953,"a":1}},"resolvedValuesByMode":{"58:0":{"resolvedValue":{"r":0.22745098173618317,"g":0.239215686917305,"b":0.2549019753932953,"a":1},"alias":null}},"scopes":["ALL_SCOPES"],"hiddenFromPublishing":false,"codeSyntax":{}},{"id":"VariableID:105:5359","name":"Color/Ccharcole/800","description":"","type":"COLOR","valuesByMode":{"58:0":{"r":0.1764705926179886,"g":0.18431372940540314,"b":0.19607843458652496,"a":1}},"resolvedValuesByMode":{"58:0":{"resolvedValue":{"r":0.1764705926179886,"g":0.18431372940540314,"b":0.19607843458652496,"a":1},"alias":null}},"scopes":["ALL_SCOPES"],"hiddenFromPublishing":false,"codeSyntax":{}},{"id":"VariableID:105:5360","name":"Color/Ccharcole/900","description":"","type":"COLOR","valuesByMode":{"58:0":{"r":0.13333334028720856,"g":0.1411764770746231,"b":0.14901961386203766,"a":1}},"resolvedValuesByMode":{"58:0":{"resolvedValue":{"r":0.13333334028720856,"g":0.1411764770746231,"b":0.14901961386203766,"a":1},"alias":null}},"scopes":["ALL_SCOPES"],"hiddenFromPublishing":false,"codeSyntax":{}},{"id":"VariableID:105:5361","name":"Color/ColdBlue/50","description":"","type":"COLOR","valuesByMode":{"58:0":{"r":0.9176470637321472,"g":0.9215686321258545,"b":0.9333333373069763,"a":1}},"resolvedValuesByMode":{"58:0":{"resolvedValue":{"r":0.9176470637321472,"g":0.9215686321258545,"b":0.9333333373069763,"a":1},"alias":null}},"scopes":["ALL_SCOPES"],"hiddenFromPublishing":false,"codeSyntax":{}},{"id":"VariableID:105:5362","name":"Color/ColdBlue/100","description":"","type":"COLOR","valuesByMode":{"58:0":{"r":0.7411764860153198,"g":0.7490196228027344,"b":0.800000011920929,"a":1}},"resolvedValuesByMode":{"58:0":{"resolvedValue":{"r":0.7411764860153198,"g":0.7490196228027344,"b":0.800000011920929,"a":1},"alias":null}},"scopes":["ALL_SCOPES"],"hiddenFromPublishing":false,"codeSyntax":{}},{"id":"VariableID:105:5363","name":"Color/ColdBlue/200","description":"","type":"COLOR","valuesByMode":{"58:0":{"r":0.615686297416687,"g":0.6313725709915161,"b":0.7019608020782471,"a":1}},"resolvedValuesByMode":{"58:0":{"resolvedValue":{"r":0.615686297416687,"g":0.6313725709915161,"b":0.7019608020782471,"a":1},"alias":null}},"scopes":["ALL_SCOPES"],"hiddenFromPublishing":false,"codeSyntax":{}},{"id":"VariableID:105:5364","name":"Color/ColdBlue/300","description":"","type":"COLOR","valuesByMode":{"58:0":{"r":0.4431372582912445,"g":0.4627451002597809,"b":0.5647059082984924,"a":1}},"resolvedValuesByMode":{"58:0":{"resolvedValue":{"r":0.4431372582912445,"g":0.4627451002597809,"b":0.5647059082984924,"a":1},"alias":null}},"scopes":["ALL_SCOPES"],"hiddenFromPublishing":false,"codeSyntax":{}},{"id":"VariableID:105:5365","name":"Color/ColdBlue/400","description":"","type":"COLOR","valuesByMode":{"58:0":{"r":0.3333333432674408,"g":0.35686275362968445,"b":0.47843137383461,"a":1}},"resolvedValuesByMode":{"58:0":{"resolvedValue":{"r":0.3333333432674408,"g":0.35686275362968445,"b":0.47843137383461,"a":1},"alias":null}},"scopes":["ALL_SCOPES"],"hiddenFromPublishing":false,"codeSyntax":{}},{"id":"VariableID:105:5366","name":"Color/ColdBlue/500","description":"","type":"COLOR","valuesByMode":{"58:0":{"r":0.16862745583057404,"g":0.19607843458652496,"b":0.3490196168422699,"a":1}},"resolvedValuesByMode":{"58:0":{"resolvedValue":{"r":0.16862745583057404,"g":0.19607843458652496,"b":0.3490196168422699,"a":1},"alias":null}},"scopes":["ALL_SCOPES"],"hiddenFromPublishing":false,"codeSyntax":{}},{"id":"VariableID:105:5367","name":"Color/ColdBlue/600","description":"","type":"COLOR","valuesByMode":{"58:0":{"r":0.15294118225574493,"g":0.18039216101169586,"b":0.3176470696926117,"a":1}},"resolvedValuesByMode":{"58:0":{"resolvedValue":{"r":0.15294118225574493,"g":0.18039216101169586,"b":0.3176470696926117,"a":1},"alias":null}},"scopes":["ALL_SCOPES"],"hiddenFromPublishing":false,"codeSyntax":{}},{"id":"VariableID:105:5368","name":"Color/ColdBlue/700","description":"","type":"COLOR","valuesByMode":{"58:0":{"r":0.12156862765550613,"g":0.1411764770746231,"b":0.24705882370471954,"a":1}},"resolvedValuesByMode":{"58:0":{"resolvedValue":{"r":0.12156862765550613,"g":0.1411764770746231,"b":0.24705882370471954,"a":1},"alias":null}},"scopes":["ALL_SCOPES"],"hiddenFromPublishing":false,"codeSyntax":{}},{"id":"VariableID:105:5369","name":"Color/ColdBlue/800","description":"","type":"COLOR","valuesByMode":{"58:0":{"r":0.0941176488995552,"g":0.10980392247438431,"b":0.1921568661928177,"a":1}},"resolvedValuesByMode":{"58:0":{"resolvedValue":{"r":0.0941176488995552,"g":0.10980392247438431,"b":0.1921568661928177,"a":1},"alias":null}},"scopes":["ALL_SCOPES"],"hiddenFromPublishing":false,"codeSyntax":{}},{"id":"VariableID:105:5370","name":"Color/ColdBlue/900","description":"","type":"COLOR","valuesByMode":{"58:0":{"r":0.07058823853731155,"g":0.08235294371843338,"b":0.14509804546833038,"a":1}},"resolvedValuesByMode":{"58:0":{"resolvedValue":{"r":0.07058823853731155,"g":0.08235294371843338,"b":0.14509804546833038,"a":1},"alias":null}},"scopes":["ALL_SCOPES"],"hiddenFromPublishing":false,"codeSyntax":{}},{"id":"VariableID:105:5371","name":"Color/Green/50","description":"","type":"COLOR","valuesByMode":{"58:0":{"r":0.9019607901573181,"g":0.9960784316062927,"b":0.929411768913269,"a":1}},"resolvedValuesByMode":{"58:0":{"resolvedValue":{"r":0.9019607901573181,"g":0.9960784316062927,"b":0.929411768913269,"a":1},"alias":null}},"scopes":["ALL_SCOPES"],"hiddenFromPublishing":false,"codeSyntax":{}},{"id":"VariableID:105:5372","name":"Color/Green/100","description":"","type":"COLOR","valuesByMode":{"58:0":{"r":0.6901960968971252,"g":0.9803921580314636,"b":0.7843137383460999,"a":1}},"resolvedValuesByMode":{"58:0":{"resolvedValue":{"r":0.6901960968971252,"g":0.9803921580314636,"b":0.7843137383460999,"a":1},"alias":null}},"scopes":["ALL_SCOPES"],"hiddenFromPublishing":false,"codeSyntax":{}},{"id":"VariableID:105:5373","name":"Color/Green/200","description":"","type":"COLOR","valuesByMode":{"58:0":{"r":0.5411764979362488,"g":0.9725490212440491,"b":0.6784313917160034,"a":1}},"resolvedValuesByMode":{"58:0":{"resolvedValue":{"r":0.5411764979362488,"g":0.9725490212440491,"b":0.6784313917160034,"a":1},"alias":null}},"scopes":["ALL_SCOPES"],"hiddenFromPublishing":false,"codeSyntax":{}},{"id":"VariableID:105:5374","name":"Color/Green/300","description":"","type":"COLOR","valuesByMode":{"58:0":{"r":0.3294117748737335,"g":0.9607843160629272,"b":0.529411792755127,"a":1}},"resolvedValuesByMode":{"58:0":{"resolvedValue":{"r":0.3294117748737335,"g":0.9607843160629272,"b":0.529411792755127,"a":1},"alias":null}},"scopes":["ALL_SCOPES"],"hiddenFromPublishing":false,"codeSyntax":{}},{"id":"VariableID:105:5375","name":"Color/Green/400","description":"","type":"COLOR","valuesByMode":{"58:0":{"r":0.20000000298023224,"g":0.9529411792755127,"b":0.43921568989753723,"a":1}},"resolvedValuesByMode":{"58:0":{"resolvedValue":{"r":0.20000000298023224,"g":0.9529411792755127,"b":0.43921568989753723,"a":1},"alias":null}},"scopes":["ALL_SCOPES"],"hiddenFromPublishing":false,"codeSyntax":{}},{"id":"VariableID:105:5376","name":"Color/Green/500","description":"","type":"COLOR","valuesByMode":{"58:0":{"r":0,"g":0.9411764740943909,"b":0.2980392277240753,"a":1}},"resolvedValuesByMode":{"58:0":{"resolvedValue":{"r":0,"g":0.9411764740943909,"b":0.2980392277240753,"a":1},"alias":null}},"scopes":["ALL_SCOPES"],"hiddenFromPublishing":false,"codeSyntax":{}},{"id":"VariableID:105:5377","name":"Color/Green/600","description":"","type":"COLOR","valuesByMode":{"58:0":{"r":0,"g":0.8549019694328308,"b":0.2705882489681244,"a":1}},"resolvedValuesByMode":{"58:0":{"resolvedValue":{"r":0,"g":0.8549019694328308,"b":0.2705882489681244,"a":1},"alias":null}},"scopes":["ALL_SCOPES"],"hiddenFromPublishing":false,"codeSyntax":{}},{"id":"VariableID:105:5378","name":"Color/Green/700","description":"","type":"COLOR","valuesByMode":{"58:0":{"r":0,"g":0.6666666865348816,"b":0.21176470816135406,"a":1}},"resolvedValuesByMode":{"58:0":{"resolvedValue":{"r":0,"g":0.6666666865348816,"b":0.21176470816135406,"a":1},"alias":null}},"scopes":["ALL_SCOPES"],"hiddenFromPublishing":false,"codeSyntax":{}},{"id":"VariableID:105:5379","name":"Color/Green/800","description":"","type":"COLOR","valuesByMode":{"58:0":{"r":0,"g":0.5176470875740051,"b":0.16470588743686676,"a":1}},"resolvedValuesByMode":{"58:0":{"resolvedValue":{"r":0,"g":0.5176470875740051,"b":0.16470588743686676,"a":1},"alias":null}},"scopes":["ALL_SCOPES"],"hiddenFromPublishing":false,"codeSyntax":{}},{"id":"VariableID:105:5380","name":"Color/Green/900","description":"","type":"COLOR","valuesByMode":{"58:0":{"r":0,"g":0.3960784375667572,"b":0.125490203499794,"a":1}},"resolvedValuesByMode":{"58:0":{"resolvedValue":{"r":0,"g":0.3960784375667572,"b":0.125490203499794,"a":1},"alias":null}},"scopes":["ALL_SCOPES"],"hiddenFromPublishing":false,"codeSyntax":{}},{"id":"VariableID:105:5381","name":"Color/Gold/50","description":"","type":"COLOR","valuesByMode":{"58:0":{"r":1,"g":0.9803921580314636,"b":0.9019607901573181,"a":1}},"resolvedValuesByMode":{"58:0":{"resolvedValue":{"r":1,"g":0.9803921580314636,"b":0.9019607901573181,"a":1},"alias":null}},"scopes":["ALL_SCOPES"],"hiddenFromPublishing":false,"codeSyntax":{}},{"id":"VariableID:105:5382","name":"Color/Gold/100","description":"","type":"COLOR","valuesByMode":{"58:0":{"r":1,"g":0.9333333373069763,"b":0.6901960968971252,"a":1}},"resolvedValuesByMode":{"58:0":{"resolvedValue":{"r":1,"g":0.9333333373069763,"b":0.6901960968971252,"a":1},"alias":null}},"scopes":["ALL_SCOPES"],"hiddenFromPublishing":false,"codeSyntax":{}},{"id":"VariableID:105:5383","name":"Color/Gold/200","description":"","type":"COLOR","valuesByMode":{"58:0":{"r":1,"g":0.9019607901573181,"b":0.5411764979362488,"a":1}},"resolvedValuesByMode":{"58:0":{"resolvedValue":{"r":1,"g":0.9019607901573181,"b":0.5411764979362488,"a":1},"alias":null}},"scopes":["ALL_SCOPES"],"hiddenFromPublishing":false,"codeSyntax":{}},{"id":"VariableID:105:5384","name":"Color/Gold/300","description":"","type":"COLOR","valuesByMode":{"58:0":{"r":1,"g":0.8549019694328308,"b":0.3294117748737335,"a":1}},"resolvedValuesByMode":{"58:0":{"resolvedValue":{"r":1,"g":0.8549019694328308,"b":0.3294117748737335,"a":1},"alias":null}},"scopes":["ALL_SCOPES"],"hiddenFromPublishing":false,"codeSyntax":{}},{"id":"VariableID:105:5385","name":"Color/Gold/400","description":"","type":"COLOR","valuesByMode":{"58:0":{"r":1,"g":0.8274509906768799,"b":0.20000000298023224,"a":1}},"resolvedValuesByMode":{"58:0":{"resolvedValue":{"r":1,"g":0.8274509906768799,"b":0.20000000298023224,"a":1},"alias":null}},"scopes":["ALL_SCOPES"],"hiddenFromPublishing":false,"codeSyntax":{}},{"id":"VariableID:105:5386","name":"Color/Gold/500","description":"","type":"COLOR","valuesByMode":{"58:0":{"r":1,"g":0.7843137383460999,"b":0,"a":1}},"resolvedValuesByMode":{"58:0":{"resolvedValue":{"r":1,"g":0.7843137383460999,"b":0,"a":1},"alias":null}},"scopes":["ALL_SCOPES"],"hiddenFromPublishing":false,"codeSyntax":{}},{"id":"VariableID:105:5387","name":"Color/Gold/600","description":"","type":"COLOR","valuesByMode":{"58:0":{"r":0.9098039269447327,"g":0.7137255072593689,"b":0,"a":1}},"resolvedValuesByMode":{"58:0":{"resolvedValue":{"r":0.9098039269447327,"g":0.7137255072593689,"b":0,"a":1},"alias":null}},"scopes":["ALL_SCOPES"],"hiddenFromPublishing":false,"codeSyntax":{}},{"id":"VariableID:105:5388","name":"Color/Gold/700","description":"","type":"COLOR","valuesByMode":{"58:0":{"r":0.7098039388656616,"g":0.5568627715110779,"b":0,"a":1}},"resolvedValuesByMode":{"58:0":{"resolvedValue":{"r":0.7098039388656616,"g":0.5568627715110779,"b":0,"a":1},"alias":null}},"scopes":["ALL_SCOPES"],"hiddenFromPublishing":false,"codeSyntax":{}},{"id":"VariableID:105:5389","name":"Color/Gold/800","description":"","type":"COLOR","valuesByMode":{"58:0":{"r":0.5490196347236633,"g":0.4313725531101227,"b":0,"a":1}},"resolvedValuesByMode":{"58:0":{"resolvedValue":{"r":0.5490196347236633,"g":0.4313725531101227,"b":0,"a":1},"alias":null}},"scopes":["ALL_SCOPES"],"hiddenFromPublishing":false,"codeSyntax":{}},{"id":"VariableID:105:5390","name":"Color/Gold/900","description":"","type":"COLOR","valuesByMode":{"58:0":{"r":0.41960784792900085,"g":0.3294117748737335,"b":0,"a":1}},"resolvedValuesByMode":{"58:0":{"resolvedValue":{"r":0.41960784792900085,"g":0.3294117748737335,"b":0,"a":1},"alias":null}},"scopes":["ALL_SCOPES"],"hiddenFromPublishing":false,"codeSyntax":{}},{"id":"VariableID:105:5391","name":"Color/Greenery/50","description":"","type":"COLOR","valuesByMode":{"58:0":{"r":0.9450980424880981,"g":0.9686274528503418,"b":0.9176470637321472,"a":1}},"resolvedValuesByMode":{"58:0":{"resolvedValue":{"r":0.9450980424880981,"g":0.9686274528503418,"b":0.9176470637321472,"a":1},"alias":null}},"scopes":["ALL_SCOPES"],"hiddenFromPublishing":false,"codeSyntax":{}},{"id":"VariableID:105:5392","name":"Color/Greenery/100","description":"","type":"COLOR","valuesByMode":{"58:0":{"r":0.8313725590705872,"g":0.9058823585510254,"b":0.7411764860153198,"a":1}},"resolvedValuesByMode":{"58:0":{"resolvedValue":{"r":0.8313725590705872,"g":0.9058823585510254,"b":0.7411764860153198,"a":1},"alias":null}},"scopes":["ALL_SCOPES"],"hiddenFromPublishing":false,"codeSyntax":{}},{"id":"VariableID:105:5393","name":"Color/Greenery/200","description":"","type":"COLOR","valuesByMode":{"58:0":{"r":0.7529411911964417,"g":0.8627451062202454,"b":0.615686297416687,"a":1}},"resolvedValuesByMode":{"58:0":{"resolvedValue":{"r":0.7529411911964417,"g":0.8627451062202454,"b":0.615686297416687,"a":1},"alias":null}},"scopes":["ALL_SCOPES"],"hiddenFromPublishing":false,"codeSyntax":{}},{"id":"VariableID:105:5394","name":"Color/Greenery/300","description":"","type":"COLOR","valuesByMode":{"58:0":{"r":0.6392157077789307,"g":0.800000011920929,"b":0.43921568989753723,"a":1}},"resolvedValuesByMode":{"58:0":{"resolvedValue":{"r":0.6392157077789307,"g":0.800000011920929,"b":0.43921568989753723,"a":1},"alias":null}},"scopes":["ALL_SCOPES"],"hiddenFromPublishing":false,"codeSyntax":{}},{"id":"VariableID:105:5395","name":"Color/Greenery/400","description":"","type":"COLOR","valuesByMode":{"58:0":{"r":0.5686274766921997,"g":0.7607843279838562,"b":0.3294117748737335,"a":1}},"resolvedValuesByMode":{"58:0":{"resolvedValue":{"r":0.5686274766921997,"g":0.7607843279838562,"b":0.3294117748737335,"a":1},"alias":null}},"scopes":["ALL_SCOPES"],"hiddenFromPublishing":false,"codeSyntax":{}},{"id":"VariableID:105:5396","name":"Color/Greenery/500","description":"","type":"COLOR","valuesByMode":{"58:0":{"r":0.4588235318660736,"g":0.7019608020782471,"b":0.16078431904315948,"a":1}},"resolvedValuesByMode":{"58:0":{"resolvedValue":{"r":0.4588235318660736,"g":0.7019608020782471,"b":0.16078431904315948,"a":1},"alias":null}},"scopes":["ALL_SCOPES"],"hiddenFromPublishing":false,"codeSyntax":{}},{"id":"VariableID:105:5397","name":"Color/Greenery/600","description":"","type":"COLOR","valuesByMode":{"58:0":{"r":0.4156862795352936,"g":0.6392157077789307,"b":0.14509804546833038,"a":1}},"resolvedValuesByMode":{"58:0":{"resolvedValue":{"r":0.4156862795352936,"g":0.6392157077789307,"b":0.14509804546833038,"a":1},"alias":null}},"scopes":["ALL_SCOPES"],"hiddenFromPublishing":false,"codeSyntax":{}},{"id":"VariableID:105:5398","name":"Color/Greenery/700","description":"","type":"COLOR","valuesByMode":{"58:0":{"r":0.32549020648002625,"g":0.49803921580314636,"b":0.11372549086809158,"a":1}},"resolvedValuesByMode":{"58:0":{"resolvedValue":{"r":0.32549020648002625,"g":0.49803921580314636,"b":0.11372549086809158,"a":1},"alias":null}},"scopes":["ALL_SCOPES"],"hiddenFromPublishing":false,"codeSyntax":{}},{"id":"VariableID:105:5399","name":"Color/Greenery/800","description":"","type":"COLOR","valuesByMode":{"58:0":{"r":0.250980406999588,"g":0.3843137323856354,"b":0.09019608050584793,"a":1}},"resolvedValuesByMode":{"58:0":{"resolvedValue":{"r":0.250980406999588,"g":0.3843137323856354,"b":0.09019608050584793,"a":1},"alias":null}},"scopes":["ALL_SCOPES"],"hiddenFromPublishing":false,"codeSyntax":{}},{"id":"VariableID:105:5400","name":"Color/Greenery/900","description":"","type":"COLOR","valuesByMode":{"58:0":{"r":0.1921568661928177,"g":0.29411765933036804,"b":0.06666667014360428,"a":1}},"resolvedValuesByMode":{"58:0":{"resolvedValue":{"r":0.1921568661928177,"g":0.29411765933036804,"b":0.06666667014360428,"a":1},"alias":null}},"scopes":["ALL_SCOPES"],"hiddenFromPublishing":false,"codeSyntax":{}},{"id":"VariableID:105:5401","name":"Color/Red/50","description":"","type":"COLOR","valuesByMode":{"58:0":{"r":0.9960784316062927,"g":0.9215686321258545,"b":0.9215686321258545,"a":1}},"resolvedValuesByMode":{"58:0":{"resolvedValue":{"r":0.9960784316062927,"g":0.9215686321258545,"b":0.9215686321258545,"a":1},"alias":null}},"scopes":["ALL_SCOPES"],"hiddenFromPublishing":false,"codeSyntax":{}},{"id":"VariableID:105:5402","name":"Color/Red/100","description":"","type":"COLOR","valuesByMode":{"58:0":{"r":0.9882352948188782,"g":0.7490196228027344,"b":0.7490196228027344,"a":1}},"resolvedValuesByMode":{"58:0":{"resolvedValue":{"r":0.9882352948188782,"g":0.7490196228027344,"b":0.7490196228027344,"a":1},"alias":null}},"scopes":["ALL_SCOPES"],"hiddenFromPublishing":false,"codeSyntax":{}},{"id":"VariableID:105:5403","name":"Color/Red/200","description":"","type":"COLOR","valuesByMode":{"58:0":{"r":0.9803921580314636,"g":0.6313725709915161,"b":0.6313725709915161,"a":1}},"resolvedValuesByMode":{"58:0":{"resolvedValue":{"r":0.9803921580314636,"g":0.6313725709915161,"b":0.6313725709915161,"a":1},"alias":null}},"scopes":["ALL_SCOPES"],"hiddenFromPublishing":false,"codeSyntax":{}},{"id":"VariableID:105:5404","name":"Color/Red/300","description":"","type":"COLOR","valuesByMode":{"58:0":{"r":0.9725490212440491,"g":0.4627451002597809,"b":0.4627451002597809,"a":1}},"resolvedValuesByMode":{"58:0":{"resolvedValue":{"r":0.9725490212440491,"g":0.4627451002597809,"b":0.4627451002597809,"a":1},"alias":null}},"scopes":["ALL_SCOPES"],"hiddenFromPublishing":false,"codeSyntax":{}},{"id":"VariableID:105:5405","name":"Color/Red/400","description":"","type":"COLOR","valuesByMode":{"58:0":{"r":0.9686274528503418,"g":0.35686275362968445,"b":0.35686275362968445,"a":1}},"resolvedValuesByMode":{"58:0":{"resolvedValue":{"r":0.9686274528503418,"g":0.35686275362968445,"b":0.35686275362968445,"a":1},"alias":null}},"scopes":["ALL_SCOPES"],"hiddenFromPublishing":false,"codeSyntax":{}},{"id":"VariableID:105:5406","name":"Color/Red/500","description":"","type":"COLOR","valuesByMode":{"58:0":{"r":0.9607843160629272,"g":0.19607843458652496,"b":0.19607843458652496,"a":1}},"resolvedValuesByMode":{"58:0":{"resolvedValue":{"r":0.9607843160629272,"g":0.19607843458652496,"b":0.19607843458652496,"a":1},"alias":null}},"scopes":["ALL_SCOPES"],"hiddenFromPublishing":false,"codeSyntax":{}},{"id":"VariableID:105:5407","name":"Color/Red/600","description":"","type":"COLOR","valuesByMode":{"58:0":{"r":0.8745098114013672,"g":0.18039216101169586,"b":0.18039216101169586,"a":1}},"resolvedValuesByMode":{"58:0":{"resolvedValue":{"r":0.8745098114013672,"g":0.18039216101169586,"b":0.18039216101169586,"a":1},"alias":null}},"scopes":["ALL_SCOPES"],"hiddenFromPublishing":false,"codeSyntax":{}},{"id":"VariableID:105:5408","name":"Color/Red/700","description":"","type":"COLOR","valuesByMode":{"58:0":{"r":0.6823529601097107,"g":0.1411764770746231,"b":0.1411764770746231,"a":1}},"resolvedValuesByMode":{"58:0":{"resolvedValue":{"r":0.6823529601097107,"g":0.1411764770746231,"b":0.1411764770746231,"a":1},"alias":null}},"scopes":["ALL_SCOPES"],"hiddenFromPublishing":false,"codeSyntax":{}},{"id":"VariableID:105:5409","name":"Color/Red/800","description":"","type":"COLOR","valuesByMode":{"58:0":{"r":0.529411792755127,"g":0.10980392247438431,"b":0.10980392247438431,"a":1}},"resolvedValuesByMode":{"58:0":{"resolvedValue":{"r":0.529411792755127,"g":0.10980392247438431,"b":0.10980392247438431,"a":1},"alias":null}},"scopes":["ALL_SCOPES"],"hiddenFromPublishing":false,"codeSyntax":{}},{"id":"VariableID:105:5410","name":"Color/Red/900","description":"","type":"COLOR","valuesByMode":{"58:0":{"r":0.40392157435417175,"g":0.08235294371843338,"b":0.08235294371843338,"a":1}},"resolvedValuesByMode":{"58:0":{"resolvedValue":{"r":0.40392157435417175,"g":0.08235294371843338,"b":0.08235294371843338,"a":1},"alias":null}},"scopes":["ALL_SCOPES"],"hiddenFromPublishing":false,"codeSyntax":{}},{"id":"VariableID:105:5411","name":"Color/Yellow/50","description":"","type":"COLOR","valuesByMode":{"58:0":{"r":0.9921568632125854,"g":0.9843137264251709,"b":0.9254902005195618,"a":1}},"resolvedValuesByMode":{"58:0":{"resolvedValue":{"r":0.9921568632125854,"g":0.9843137264251709,"b":0.9254902005195618,"a":1},"alias":null}},"scopes":["ALL_SCOPES"],"hiddenFromPublishing":false,"codeSyntax":{}},{"id":"VariableID:105:5412","name":"Color/Yellow/100","description":"","type":"COLOR","valuesByMode":{"58:0":{"r":0.9764705896377563,"g":0.9490196108818054,"b":0.7647058963775635,"a":1}},"resolvedValuesByMode":{"58:0":{"resolvedValue":{"r":0.9764705896377563,"g":0.9490196108818054,"b":0.7647058963775635,"a":1},"alias":null}},"scopes":["ALL_SCOPES"],"hiddenFromPublishing":false,"codeSyntax":{}},{"id":"VariableID:105:5413","name":"Color/Yellow/200","description":"","type":"COLOR","valuesByMode":{"58:0":{"r":0.9647058844566345,"g":0.9215686321258545,"b":0.6470588445663452,"a":1}},"resolvedValuesByMode":{"58:0":{"resolvedValue":{"r":0.9647058844566345,"g":0.9215686321258545,"b":0.6470588445663452,"a":1},"alias":null}},"scopes":["ALL_SCOPES"],"hiddenFromPublishing":false,"codeSyntax":{}},{"id":"VariableID:105:5414","name":"Color/Yellow/300","description":"","type":"COLOR","valuesByMode":{"58:0":{"r":0.9490196108818054,"g":0.886274516582489,"b":0.48627451062202454,"a":1}},"resolvedValuesByMode":{"58:0":{"resolvedValue":{"r":0.9490196108818054,"g":0.886274516582489,"b":0.48627451062202454,"a":1},"alias":null}},"scopes":["ALL_SCOPES"],"hiddenFromPublishing":false,"codeSyntax":{}},{"id":"VariableID:105:5415","name":"Color/Yellow/400","description":"","type":"COLOR","valuesByMode":{"58:0":{"r":0.9411764740943909,"g":0.8666666746139526,"b":0.38823530077934265,"a":1}},"resolvedValuesByMode":{"58:0":{"resolvedValue":{"r":0.9411764740943909,"g":0.8666666746139526,"b":0.38823530077934265,"a":1},"alias":null}},"scopes":["ALL_SCOPES"],"hiddenFromPublishing":false,"codeSyntax":{}},{"id":"VariableID:105:5416","name":"Color/Yellow/500","description":"","type":"COLOR","valuesByMode":{"58:0":{"r":0.9254902005195618,"g":0.8313725590705872,"b":0.23529411852359772,"a":1}},"resolvedValuesByMode":{"58:0":{"resolvedValue":{"r":0.9254902005195618,"g":0.8313725590705872,"b":0.23529411852359772,"a":1},"alias":null}},"scopes":["ALL_SCOPES"],"hiddenFromPublishing":false,"codeSyntax":{}},{"id":"VariableID:105:5417","name":"Color/Yellow/600","description":"","type":"COLOR","valuesByMode":{"58:0":{"r":0.843137264251709,"g":0.7568627595901489,"b":0.21568627655506134,"a":1}},"resolvedValuesByMode":{"58:0":{"resolvedValue":{"r":0.843137264251709,"g":0.7568627595901489,"b":0.21568627655506134,"a":1},"alias":null}},"scopes":["ALL_SCOPES"],"hiddenFromPublishing":false,"codeSyntax":{}},{"id":"VariableID:105:5418","name":"Color/Yellow/700","description":"","type":"COLOR","valuesByMode":{"58:0":{"r":0.658823549747467,"g":0.5921568870544434,"b":0.16862745583057404,"a":1}},"resolvedValuesByMode":{"58:0":{"resolvedValue":{"r":0.658823549747467,"g":0.5921568870544434,"b":0.16862745583057404,"a":1},"alias":null}},"scopes":["ALL_SCOPES"],"hiddenFromPublishing":false,"codeSyntax":{}},{"id":"VariableID:105:5419","name":"Color/Yellow/800","description":"","type":"COLOR","valuesByMode":{"58:0":{"r":0.5098039507865906,"g":0.4588235318660736,"b":0.12941177189350128,"a":1}},"resolvedValuesByMode":{"58:0":{"resolvedValue":{"r":0.5098039507865906,"g":0.4588235318660736,"b":0.12941177189350128,"a":1},"alias":null}},"scopes":["ALL_SCOPES"],"hiddenFromPublishing":false,"codeSyntax":{}},{"id":"VariableID:105:5420","name":"Color/Yellow/900","description":"","type":"COLOR","valuesByMode":{"58:0":{"r":0.38823530077934265,"g":0.3490196168422699,"b":0.09803921729326248,"a":1}},"resolvedValuesByMode":{"58:0":{"resolvedValue":{"r":0.38823530077934265,"g":0.3490196168422699,"b":0.09803921729326248,"a":1},"alias":null}},"scopes":["ALL_SCOPES"],"hiddenFromPublishing":false,"codeSyntax":{}},{"id":"VariableID:105:5421","name":"Color/Orange/50","description":"","type":"COLOR","valuesByMode":{"58:0":{"r":1,"g":0.9647058844566345,"b":0.9137254953384399,"a":1}},"resolvedValuesByMode":{"58:0":{"resolvedValue":{"r":1,"g":0.9647058844566345,"b":0.9137254953384399,"a":1},"alias":null}},"scopes":["ALL_SCOPES"],"hiddenFromPublishing":false,"codeSyntax":{}},{"id":"VariableID:105:5422","name":"Color/Orange/100","description":"","type":"COLOR","valuesByMode":{"58:0":{"r":1,"g":0.886274516582489,"b":0.729411780834198,"a":1}},"resolvedValuesByMode":{"58:0":{"resolvedValue":{"r":1,"g":0.886274516582489,"b":0.729411780834198,"a":1},"alias":null}},"scopes":["ALL_SCOPES"],"hiddenFromPublishing":false,"codeSyntax":{}},{"id":"VariableID:105:5423","name":"Color/Orange/200","description":"","type":"COLOR","valuesByMode":{"58:0":{"r":1,"g":0.8313725590705872,"b":0.5960784554481506,"a":1}},"resolvedValuesByMode":{"58:0":{"resolvedValue":{"r":1,"g":0.8313725590705872,"b":0.5960784554481506,"a":1},"alias":null}},"scopes":["ALL_SCOPES"],"hiddenFromPublishing":false,"codeSyntax":{}},{"id":"VariableID:105:5424","name":"Color/Orange/300","description":"","type":"COLOR","valuesByMode":{"58:0":{"r":1,"g":0.7568627595901489,"b":0.4117647111415863,"a":1}},"resolvedValuesByMode":{"58:0":{"resolvedValue":{"r":1,"g":0.7568627595901489,"b":0.4117647111415863,"a":1},"alias":null}},"scopes":["ALL_SCOPES"],"hiddenFromPublishing":false,"codeSyntax":{}},{"id":"VariableID:105:5425","name":"Color/Orange/400","description":"","type":"COLOR","valuesByMode":{"58:0":{"r":1,"g":0.7098039388656616,"b":0.2980392277240753,"a":1}},"resolvedValuesByMode":{"58:0":{"resolvedValue":{"r":1,"g":0.7098039388656616,"b":0.2980392277240753,"a":1},"alias":null}},"scopes":["ALL_SCOPES"],"hiddenFromPublishing":false,"codeSyntax":{}},{"id":"VariableID:105:5426","name":"Color/Orange/500","description":"","type":"COLOR","valuesByMode":{"58:0":{"r":1,"g":0.6352941393852234,"b":0.12156862765550613,"a":1}},"resolvedValuesByMode":{"58:0":{"resolvedValue":{"r":1,"g":0.6352941393852234,"b":0.12156862765550613,"a":1},"alias":null}},"scopes":["ALL_SCOPES"],"hiddenFromPublishing":false,"codeSyntax":{}},{"id":"VariableID:105:5427","name":"Color/Orange/600","description":"","type":"COLOR","valuesByMode":{"58:0":{"r":0.9098039269447327,"g":0.5764706134796143,"b":0.10980392247438431,"a":1}},"resolvedValuesByMode":{"58:0":{"resolvedValue":{"r":0.9098039269447327,"g":0.5764706134796143,"b":0.10980392247438431,"a":1},"alias":null}},"scopes":["ALL_SCOPES"],"hiddenFromPublishing":false,"codeSyntax":{}},{"id":"VariableID:105:5428","name":"Color/Orange/700","description":"","type":"COLOR","valuesByMode":{"58:0":{"r":0.7098039388656616,"g":0.45098039507865906,"b":0.08627451211214066,"a":1}},"resolvedValuesByMode":{"58:0":{"resolvedValue":{"r":0.7098039388656616,"g":0.45098039507865906,"b":0.08627451211214066,"a":1},"alias":null}},"scopes":["ALL_SCOPES"],"hiddenFromPublishing":false,"codeSyntax":{}},{"id":"VariableID:105:5429","name":"Color/Orange/800","description":"","type":"COLOR","valuesByMode":{"58:0":{"r":0.5490196347236633,"g":0.3490196168422699,"b":0.06666667014360428,"a":1}},"resolvedValuesByMode":{"58:0":{"resolvedValue":{"r":0.5490196347236633,"g":0.3490196168422699,"b":0.06666667014360428,"a":1},"alias":null}},"scopes":["ALL_SCOPES"],"hiddenFromPublishing":false,"codeSyntax":{}},{"id":"VariableID:105:5430","name":"Color/Orange/900","description":"","type":"COLOR","valuesByMode":{"58:0":{"r":0.41960784792900085,"g":0.2666666805744171,"b":0.05098039284348488,"a":1}},"resolvedValuesByMode":{"58:0":{"resolvedValue":{"r":0.41960784792900085,"g":0.2666666805744171,"b":0.05098039284348488,"a":1},"alias":null}},"scopes":["ALL_SCOPES"],"hiddenFromPublishing":false,"codeSyntax":{}},{"id":"VariableID:105:5431","name":"Color/Blue/50","description":"","type":"COLOR","valuesByMode":{"58:0":{"r":0.929411768913269,"g":0.9764705896377563,"b":1,"a":1}},"resolvedValuesByMode":{"58:0":{"resolvedValue":{"r":0.929411768913269,"g":0.9764705896377563,"b":1,"a":1},"alias":null}},"scopes":["ALL_SCOPES"],"hiddenFromPublishing":false,"codeSyntax":{}},{"id":"VariableID:105:5432","name":"Color/Blue/100","description":"","type":"COLOR","valuesByMode":{"58:0":{"r":0.7764706015586853,"g":0.9254902005195618,"b":1,"a":1}},"resolvedValuesByMode":{"58:0":{"resolvedValue":{"r":0.7764706015586853,"g":0.9254902005195618,"b":1,"a":1},"alias":null}},"scopes":["ALL_SCOPES"],"hiddenFromPublishing":false,"codeSyntax":{}},{"id":"VariableID:105:5433","name":"Color/Blue/200","description":"","type":"COLOR","valuesByMode":{"58:0":{"r":0.6666666865348816,"g":0.8901960849761963,"b":1,"a":1}},"resolvedValuesByMode":{"58:0":{"resolvedValue":{"r":0.6666666865348816,"g":0.8901960849761963,"b":1,"a":1},"alias":null}},"scopes":["ALL_SCOPES"],"hiddenFromPublishing":false,"codeSyntax":{}},{"id":"VariableID:105:5434","name":"Color/Blue/300","description":"","type":"COLOR","valuesByMode":{"58:0":{"r":0.5176470875740051,"g":0.8392156958580017,"b":1,"a":1}},"resolvedValuesByMode":{"58:0":{"resolvedValue":{"r":0.5176470875740051,"g":0.8392156958580017,"b":1,"a":1},"alias":null}},"scopes":["ALL_SCOPES"],"hiddenFromPublishing":false,"codeSyntax":{}},{"id":"VariableID:105:5435","name":"Color/Blue/400","description":"","type":"COLOR","valuesByMode":{"58:0":{"r":0.42352941632270813,"g":0.8078431487083435,"b":1,"a":1}},"resolvedValuesByMode":{"58:0":{"resolvedValue":{"r":0.42352941632270813,"g":0.8078431487083435,"b":1,"a":1},"alias":null}},"scopes":["ALL_SCOPES"],"hiddenFromPublishing":false,"codeSyntax":{}},{"id":"VariableID:105:5436","name":"Color/Blue/500","description":"","type":"COLOR","valuesByMode":{"58:0":{"r":0.27843138575553894,"g":0.7607843279838562,"b":1,"a":1}},"resolvedValuesByMode":{"58:0":{"resolvedValue":{"r":0.27843138575553894,"g":0.7607843279838562,"b":1,"a":1},"alias":null}},"scopes":["ALL_SCOPES"],"hiddenFromPublishing":false,"codeSyntax":{}},{"id":"VariableID:105:5437","name":"Color/Blue/600","description":"","type":"COLOR","valuesByMode":{"58:0":{"r":0.2549019753932953,"g":0.6941176652908325,"b":0.9098039269447327,"a":1}},"resolvedValuesByMode":{"58:0":{"resolvedValue":{"r":0.2549019753932953,"g":0.6941176652908325,"b":0.9098039269447327,"a":1},"alias":null}},"scopes":["ALL_SCOPES"],"hiddenFromPublishing":false,"codeSyntax":{}},{"id":"VariableID:105:5438","name":"Color/Blue/700","description":"","type":"COLOR","valuesByMode":{"58:0":{"r":0.19607843458652496,"g":0.5411764979362488,"b":0.7098039388656616,"a":1}},"resolvedValuesByMode":{"58:0":{"resolvedValue":{"r":0.19607843458652496,"g":0.5411764979362488,"b":0.7098039388656616,"a":1},"alias":null}},"scopes":["ALL_SCOPES"],"hiddenFromPublishing":false,"codeSyntax":{}},{"id":"VariableID:105:5439","name":"Color/Blue/800","description":"","type":"COLOR","valuesByMode":{"58:0":{"r":0.15294118225574493,"g":0.41960784792900085,"b":0.5490196347236633,"a":1}},"resolvedValuesByMode":{"58:0":{"resolvedValue":{"r":0.15294118225574493,"g":0.41960784792900085,"b":0.5490196347236633,"a":1},"alias":null}},"scopes":["ALL_SCOPES"],"hiddenFromPublishing":false,"codeSyntax":{}},{"id":"VariableID:105:5440","name":"Color/Blue/900","description":"","type":"COLOR","valuesByMode":{"58:0":{"r":0.11764705926179886,"g":0.3176470696926117,"b":0.41960784792900085,"a":1}},"resolvedValuesByMode":{"58:0":{"resolvedValue":{"r":0.11764705926179886,"g":0.3176470696926117,"b":0.41960784792900085,"a":1},"alias":null}},"scopes":["ALL_SCOPES"],"hiddenFromPublishing":false,"codeSyntax":{}},{"id":"VariableID:151:6266","name":"typography/font weight/light","description":"","type":"STRING","valuesByMode":{"58:0":"light"},"resolvedValuesByMode":{"58:0":{"resolvedValue":"light","alias":null}},"scopes":["ALL_SCOPES"],"hiddenFromPublishing":false,"codeSyntax":{}},{"id":"VariableID:151:6267","name":"typography/font weight/regular","description":"","type":"STRING","valuesByMode":{"58:0":"regular"},"resolvedValuesByMode":{"58:0":{"resolvedValue":"regular","alias":null}},"scopes":["ALL_SCOPES"],"hiddenFromPublishing":false,"codeSyntax":{}},{"id":"VariableID:151:6268","name":"typography/font weight/medium","description":"","type":"STRING","valuesByMode":{"58:0":"medium"},"resolvedValuesByMode":{"58:0":{"resolvedValue":"medium","alias":null}},"scopes":["ALL_SCOPES"],"hiddenFromPublishing":false,"codeSyntax":{}},{"id":"VariableID:151:6269","name":"typography/font weight/semibold","description":"","type":"STRING","valuesByMode":{"58:0":"semibold"},"resolvedValuesByMode":{"58:0":{"resolvedValue":"semibold","alias":null}},"scopes":["ALL_SCOPES"],"hiddenFromPublishing":false,"codeSyntax":{}},{"id":"VariableID:151:6270","name":"typography/font weight/bold","description":"","type":"STRING","valuesByMode":{"58:0":"bold"},"resolvedValuesByMode":{"58:0":{"resolvedValue":"bold","alias":null}},"scopes":["ALL_SCOPES"],"hiddenFromPublishing":false,"codeSyntax":{}},{"id":"VariableID:151:6271","name":"typography/font family/heading","description":"","type":"STRING","valuesByMode":{"58:0":"IBM Plex Sans Thai"},"resolvedValuesByMode":{"58:0":{"resolvedValue":"IBM Plex Sans Thai","alias":null}},"scopes":["ALL_SCOPES"],"hiddenFromPublishing":false,"codeSyntax":{}},{"id":"VariableID:151:6272","name":"typography/font family/body","description":"","type":"STRING","valuesByMode":{"58:0":"IBM Plex Sans Thai"},"resolvedValuesByMode":{"58:0":{"resolvedValue":"IBM Plex Sans Thai","alias":null}},"scopes":["ALL_SCOPES"],"hiddenFromPublishing":false,"codeSyntax":{}},{"id":"VariableID:151:7756","name":"scale/0","description":"","type":"FLOAT","valuesByMode":{"58:0":0},"resolvedValuesByMode":{"58:0":{"resolvedValue":0,"alias":null}},"scopes":["ALL_SCOPES"],"hiddenFromPublishing":false,"codeSyntax":{}},{"id":"VariableID:151:7757","name":"scale/25","description":"","type":"FLOAT","valuesByMode":{"58:0":1},"resolvedValuesByMode":{"58:0":{"resolvedValue":1,"alias":null}},"scopes":["ALL_SCOPES"],"hiddenFromPublishing":false,"codeSyntax":{}},{"id":"VariableID:151:7758","name":"scale/50","description":"","type":"FLOAT","valuesByMode":{"58:0":2},"resolvedValuesByMode":{"58:0":{"resolvedValue":2,"alias":null}},"scopes":["ALL_SCOPES"],"hiddenFromPublishing":false,"codeSyntax":{}},{"id":"VariableID:151:7759","name":"scale/100","description":"","type":"FLOAT","valuesByMode":{"58:0":4},"resolvedValuesByMode":{"58:0":{"resolvedValue":4,"alias":null}},"scopes":["ALL_SCOPES"],"hiddenFromPublishing":false,"codeSyntax":{}},{"id":"VariableID:151:7760","name":"scale/150","description":"","type":"FLOAT","valuesByMode":{"58:0":6},"resolvedValuesByMode":{"58:0":{"resolvedValue":6,"alias":null}},"scopes":["ALL_SCOPES"],"hiddenFromPublishing":false,"codeSyntax":{}},{"id":"VariableID:151:7761","name":"scale/200","description":"","type":"FLOAT","valuesByMode":{"58:0":8},"resolvedValuesByMode":{"58:0":{"resolvedValue":8,"alias":null}},"scopes":["ALL_SCOPES"],"hiddenFromPublishing":false,"codeSyntax":{}},{"id":"VariableID:151:7762","name":"scale/250","description":"","type":"FLOAT","valuesByMode":{"58:0":10},"resolvedValuesByMode":{"58:0":{"resolvedValue":10,"alias":null}},"scopes":["ALL_SCOPES"],"hiddenFromPublishing":false,"codeSyntax":{}},{"id":"VariableID:151:7763","name":"scale/300","description":"","type":"FLOAT","valuesByMode":{"58:0":12},"resolvedValuesByMode":{"58:0":{"resolvedValue":12,"alias":null}},"scopes":["ALL_SCOPES"],"hiddenFromPublishing":false,"codeSyntax":{}},{"id":"VariableID:151:7764","name":"scale/350","description":"","type":"FLOAT","valuesByMode":{"58:0":14},"resolvedValuesByMode":{"58:0":{"resolvedValue":14,"alias":null}},"scopes":["ALL_SCOPES"],"hiddenFromPublishing":false,"codeSyntax":{}},{"id":"VariableID:151:7765","name":"scale/400","description":"","type":"FLOAT","valuesByMode":{"58:0":16},"resolvedValuesByMode":{"58:0":{"resolvedValue":16,"alias":null}},"scopes":["ALL_SCOPES"],"hiddenFromPublishing":false,"codeSyntax":{}},{"id":"VariableID:151:7766","name":"scale/900","description":"","type":"FLOAT","valuesByMode":{"58:0":36},"resolvedValuesByMode":{"58:0":{"resolvedValue":36,"alias":null}},"scopes":["ALL_SCOPES"],"hiddenFromPublishing":false,"codeSyntax":{}},{"id":"VariableID:151:7767","name":"scale/950","description":"","type":"FLOAT","valuesByMode":{"58:0":38},"resolvedValuesByMode":{"58:0":{"resolvedValue":38,"alias":null}},"scopes":["ALL_SCOPES"],"hiddenFromPublishing":false,"codeSyntax":{}},{"id":"VariableID:151:7768","name":"scale/1000","description":"","type":"FLOAT","valuesByMode":{"58:0":40},"resolvedValuesByMode":{"58:0":{"resolvedValue":40,"alias":null}},"scopes":["ALL_SCOPES"],"hiddenFromPublishing":false,"codeSyntax":{}},{"id":"VariableID:151:7769","name":"scale/1050","description":"","type":"FLOAT","valuesByMode":{"58:0":42},"resolvedValuesByMode":{"58:0":{"resolvedValue":42,"alias":null}},"scopes":["ALL_SCOPES"],"hiddenFromPublishing":false,"codeSyntax":{}},{"id":"VariableID:151:7770","name":"scale/1100","description":"","type":"FLOAT","valuesByMode":{"58:0":44},"resolvedValuesByMode":{"58:0":{"resolvedValue":44,"alias":null}},"scopes":["ALL_SCOPES"],"hiddenFromPublishing":false,"codeSyntax":{}},{"id":"VariableID:151:7771","name":"scale/1200","description":"","type":"FLOAT","valuesByMode":{"58:0":48},"resolvedValuesByMode":{"58:0":{"resolvedValue":48,"alias":null}},"scopes":["ALL_SCOPES"],"hiddenFromPublishing":false,"codeSyntax":{}},{"id":"VariableID:151:7773","name":"scale/450","description":"","type":"FLOAT","valuesByMode":{"58:0":18},"resolvedValuesByMode":{"58:0":{"resolvedValue":18,"alias":null}},"scopes":["ALL_SCOPES"],"hiddenFromPublishing":false,"codeSyntax":{}},{"id":"VariableID:151:7774","name":"scale/500","description":"","type":"FLOAT","valuesByMode":{"58:0":20},"resolvedValuesByMode":{"58:0":{"resolvedValue":20,"alias":null}},"scopes":["ALL_SCOPES"],"hiddenFromPublishing":false,"codeSyntax":{}},{"id":"VariableID:151:7775","name":"scale/550","description":"","type":"FLOAT","valuesByMode":{"58:0":22},"resolvedValuesByMode":{"58:0":{"resolvedValue":22,"alias":null}},"scopes":["ALL_SCOPES"],"hiddenFromPublishing":false,"codeSyntax":{}},{"id":"VariableID:151:7776","name":"scale/600","description":"","type":"FLOAT","valuesByMode":{"58:0":24},"resolvedValuesByMode":{"58:0":{"resolvedValue":24,"alias":null}},"scopes":["ALL_SCOPES"],"hiddenFromPublishing":false,"codeSyntax":{}},{"id":"VariableID:151:7777","name":"scale/650","description":"","type":"FLOAT","valuesByMode":{"58:0":26},"resolvedValuesByMode":{"58:0":{"resolvedValue":26,"alias":null}},"scopes":["ALL_SCOPES"],"hiddenFromPublishing":false,"codeSyntax":{}},{"id":"VariableID:151:7778","name":"scale/700","description":"","type":"FLOAT","valuesByMode":{"58:0":28},"resolvedValuesByMode":{"58:0":{"resolvedValue":28,"alias":null}},"scopes":["ALL_SCOPES"],"hiddenFromPublishing":false,"codeSyntax":{}},{"id":"VariableID:151:7779","name":"scale/750","description":"","type":"FLOAT","valuesByMode":{"58:0":30},"resolvedValuesByMode":{"58:0":{"resolvedValue":30,"alias":null}},"scopes":["ALL_SCOPES"],"hiddenFromPublishing":false,"codeSyntax":{}},{"id":"VariableID:151:7780","name":"scale/800","description":"","type":"FLOAT","valuesByMode":{"58:0":32},"resolvedValuesByMode":{"58:0":{"resolvedValue":32,"alias":null}},"scopes":["ALL_SCOPES"],"hiddenFromPublishing":false,"codeSyntax":{}},{"id":"VariableID:151:7781","name":"scale/850","description":"","type":"FLOAT","valuesByMode":{"58:0":34},"resolvedValuesByMode":{"58:0":{"resolvedValue":34,"alias":null}},"scopes":["ALL_SCOPES"],"hiddenFromPublishing":false,"codeSyntax":{}},{"id":"VariableID:151:7782","name":"scale/1400","description":"","type":"FLOAT","valuesByMode":{"58:0":56},"resolvedValuesByMode":{"58:0":{"resolvedValue":56,"alias":null}},"scopes":["ALL_SCOPES"],"hiddenFromPublishing":false,"codeSyntax":{}},{"id":"VariableID:151:7783","name":"scale/1600","description":"","type":"FLOAT","valuesByMode":{"58:0":64},"resolvedValuesByMode":{"58:0":{"resolvedValue":64,"alias":null}},"scopes":["ALL_SCOPES"],"hiddenFromPublishing":false,"codeSyntax":{}},{"id":"VariableID:151:7784","name":"scale/1800","description":"","type":"FLOAT","valuesByMode":{"58:0":72},"resolvedValuesByMode":{"58:0":{"resolvedValue":72,"alias":null}},"scopes":["ALL_SCOPES"],"hiddenFromPublishing":false,"codeSyntax":{}},{"id":"VariableID:151:7785","name":"scale/9999","description":"","type":"FLOAT","valuesByMode":{"58:0":999},"resolvedValuesByMode":{"58:0":{"resolvedValue":999,"alias":null}},"scopes":["ALL_SCOPES"],"hiddenFromPublishing":false,"codeSyntax":{}},{"id":"VariableID:210:472","name":"scale/2000","description":"","type":"FLOAT","valuesByMode":{"58:0":80},"resolvedValuesByMode":{"58:0":{"resolvedValue":80,"alias":null}},"scopes":["ALL_SCOPES"],"hiddenFromPublishing":false,"codeSyntax":{}},{"id":"VariableID:210:473","name":"scale/2200","description":"","type":"FLOAT","valuesByMode":{"58:0":88},"resolvedValuesByMode":{"58:0":{"resolvedValue":88,"alias":null}},"scopes":["ALL_SCOPES"],"hiddenFromPublishing":false,"codeSyntax":{}},{"id":"VariableID:210:474","name":"scale/2400","description":"","type":"FLOAT","valuesByMode":{"58:0":96},"resolvedValuesByMode":{"58:0":{"resolvedValue":96,"alias":null}},"scopes":["ALL_SCOPES"],"hiddenFromPublishing":false,"codeSyntax":{}},{"id":"VariableID:210:475","name":"scale/2600","description":"","type":"FLOAT","valuesByMode":{"58:0":112},"resolvedValuesByMode":{"58:0":{"resolvedValue":112,"alias":null}},"scopes":["ALL_SCOPES"],"hiddenFromPublishing":false,"codeSyntax":{}},{"id":"VariableID:210:476","name":"scale/2800","description":"","type":"FLOAT","valuesByMode":{"58:0":128},"resolvedValuesByMode":{"58:0":{"resolvedValue":128,"alias":null}},"scopes":["ALL_SCOPES"],"hiddenFromPublishing":false,"codeSyntax":{}},{"id":"VariableID:210:477","name":"scale/3000","description":"","type":"FLOAT","valuesByMode":{"58:0":144},"resolvedValuesByMode":{"58:0":{"resolvedValue":144,"alias":null}},"scopes":["ALL_SCOPES"],"hiddenFromPublishing":false,"codeSyntax":{}}]}